{
  "updatedAt": "2026-07-01T23:39:42.530Z",
  "source": "ESPN scoreboard (unofficial)",
  "groups": {
    "A": [
      "Mexico",
      "South Africa",
      "South Korea",
      "Czechia"
    ],
    "B": [
      "Canada",
      "Bosnia and Herzegovina",
      "Qatar",
      "Switzerland"
    ],
    "C": [
      "Brazil",
      "Morocco",
      "Haiti",
      "Scotland"
    ],
    "D": [
      "United States",
      "Paraguay",
      "Australia",
      "Turkiye"
    ],
    "E": [
      "Germany",
      "Curacao",
      "Cote d'Ivoire",
      "Ecuador"
    ],
    "F": [
      "Netherlands",
      "Japan",
      "Sweden",
      "Tunisia"
    ],
    "G": [
      "Belgium",
      "Egypt",
      "Iran",
      "New Zealand"
    ],
    "H": [
      "Spain",
      "Cape Verde",
      "Saudi Arabia",
      "Uruguay"
    ],
    "I": [
      "France",
      "Senegal",
      "Iraq",
      "Norway"
    ],
    "J": [
      "Argentina",
      "Algeria",
      "Austria",
      "Jordan"
    ],
    "K": [
      "Portugal",
      "DR Congo",
      "Uzbekistan",
      "Colombia"
    ],
    "L": [
      "England",
      "Croatia",
      "Ghana",
      "Panama"
    ]
  },
  "matches": [
    {
      "date": "Jun 11",
      "isoDate": "2026-06-11",
      "time": "FT",
      "group": "A",
      "home": "Mexico",
      "away": "South Africa",
      "venue": "Mexico City",
      "hs": 2,
      "as": 0,
      "statusShort": "FT"
    },
    {
      "date": "Jun 11",
      "isoDate": "2026-06-11",
      "time": "FT",
      "group": "A",
      "home": "South Korea",
      "away": "Czechia",
      "venue": "Guadalajara",
      "hs": 2,
      "as": 1,
      "statusShort": "FT"
    },
    {
      "date": "Jun 12",
      "isoDate": "2026-06-12",
      "time": "FT",
      "group": "B",
      "home": "Canada",
      "away": "Bosnia and Herzegovina",
      "venue": "Toronto",
      "hs": 1,
      "as": 1,
      "statusShort": "FT"
    },
    {
      "date": "Jun 12",
      "isoDate": "2026-06-12",
      "time": "FT",
      "group": "D",
      "home": "United States",
      "away": "Paraguay",
      "venue": "Los Angeles",
      "hs": 4,
      "as": 1,
      "statusShort": "FT"
    },
    {
      "date": "Jun 13",
      "isoDate": "2026-06-13",
      "time": "FT",
      "group": "D",
      "home": "Australia",
      "away": "Turkiye",
      "venue": "Vancouver",
      "hs": 2,
      "as": 0,
      "statusShort": "FT"
    },
    {
      "date": "Jun 13",
      "isoDate": "2026-06-13",
      "time": "FT",
      "group": "C",
      "home": "Brazil",
      "away": "Morocco",
      "venue": "New York/New Jersey",
      "hs": 1,
      "as": 1,
      "statusShort": "FT"
    },
    {
      "date": "Jun 13",
      "isoDate": "2026-06-13",
      "time": "FT",
      "group": "C",
      "home": "Haiti",
      "away": "Scotland",
      "venue": "Boston",
      "hs": 0,
      "as": 1,
      "statusShort": "FT"
    },
    {
      "date": "Jun 13",
      "isoDate": "2026-06-13",
      "time": "FT",
      "group": "B",
      "home": "Qatar",
      "away": "Switzerland",
      "venue": "San Francisco Bay Area",
      "hs": 1,
      "as": 1,
      "statusShort": "FT"
    },
    {
      "date": "Jun 14",
      "isoDate": "2026-06-14",
      "time": "FT",
      "group": "E",
      "home": "Cote d'Ivoire",
      "away": "Ecuador",
      "venue": "Philadelphia",
      "hs": 1,
      "as": 0,
      "statusShort": "FT"
    },
    {
      "date": "Jun 14",
      "isoDate": "2026-06-14",
      "time": "FT",
      "group": "E",
      "home": "Germany",
      "away": "Curacao",
      "venue": "Houston",
      "hs": 7,
      "as": 1,
      "statusShort": "FT"
    },
    {
      "date": "Jun 14",
      "isoDate": "2026-06-14",
      "time": "FT",
      "group": "F",
      "home": "Netherlands",
      "away": "Japan",
      "venue": "Dallas",
      "hs": 2,
      "as": 2,
      "statusShort": "FT"
    },
    {
      "date": "Jun 14",
      "isoDate": "2026-06-14",
      "time": "FT",
      "group": "F",
      "home": "Sweden",
      "away": "Tunisia",
      "venue": "Monterrey",
      "hs": 5,
      "as": 1,
      "statusShort": "FT"
    },
    {
      "date": "Jun 15",
      "isoDate": "2026-06-15",
      "time": "FT",
      "group": "G",
      "home": "Belgium",
      "away": "Egypt",
      "venue": "Seattle",
      "hs": 1,
      "as": 1,
      "statusShort": "FT"
    },
    {
      "date": "Jun 15",
      "isoDate": "2026-06-15",
      "time": "FT",
      "group": "G",
      "home": "Iran",
      "away": "New Zealand",
      "venue": "Los Angeles",
      "hs": 2,
      "as": 2,
      "statusShort": "FT"
    },
    {
      "date": "Jun 15",
      "isoDate": "2026-06-15",
      "time": "FT",
      "group": "H",
      "home": "Saudi Arabia",
      "away": "Uruguay",
      "venue": "Miami",
      "hs": 1,
      "as": 1,
      "statusShort": "FT"
    },
    {
      "date": "Jun 15",
      "isoDate": "2026-06-15",
      "time": "FT",
      "group": "H",
      "home": "Spain",
      "away": "Cape Verde",
      "venue": "Atlanta",
      "hs": 0,
      "as": 0,
      "statusShort": "FT"
    },
    {
      "date": "Jun 16",
      "isoDate": "2026-06-16",
      "time": "FT",
      "group": "J",
      "home": "Argentina",
      "away": "Algeria",
      "venue": "Kansas City",
      "hs": 3,
      "as": 0,
      "statusShort": "FT"
    },
    {
      "date": "Jun 16",
      "isoDate": "2026-06-16",
      "time": "FT",
      "group": "J",
      "home": "Austria",
      "away": "Jordan",
      "venue": "San Francisco Bay Area",
      "hs": 3,
      "as": 1,
      "statusShort": "FT"
    },
    {
      "date": "Jun 16",
      "isoDate": "2026-06-16",
      "time": "FT",
      "group": "I",
      "home": "France",
      "away": "Senegal",
      "venue": "New York/New Jersey",
      "hs": 3,
      "as": 1,
      "statusShort": "FT"
    },
    {
      "date": "Jun 16",
      "isoDate": "2026-06-16",
      "time": "FT",
      "group": "I",
      "home": "Iraq",
      "away": "Norway",
      "venue": "Boston",
      "hs": 1,
      "as": 4,
      "statusShort": "FT"
    },
    {
      "date": "Jun 17",
      "isoDate": "2026-06-17",
      "time": "FT",
      "group": "L",
      "home": "England",
      "away": "Croatia",
      "venue": "Dallas",
      "hs": 4,
      "as": 2,
      "statusShort": "FT"
    },
    {
      "date": "Jun 17",
      "isoDate": "2026-06-17",
      "time": "FT",
      "group": "L",
      "home": "Ghana",
      "away": "Panama",
      "venue": "Toronto",
      "hs": 1,
      "as": 0,
      "statusShort": "FT"
    },
    {
      "date": "Jun 17",
      "isoDate": "2026-06-17",
      "time": "FT",
      "group": "K",
      "home": "Portugal",
      "away": "DR Congo",
      "venue": "Houston",
      "hs": 1,
      "as": 1,
      "statusShort": "FT"
    },
    {
      "date": "Jun 17",
      "isoDate": "2026-06-17",
      "time": "FT",
      "group": "K",
      "home": "Uzbekistan",
      "away": "Colombia",
      "venue": "Mexico City",
      "hs": 1,
      "as": 3,
      "statusShort": "FT"
    },
    {
      "date": "Jun 18",
      "isoDate": "2026-06-18",
      "time": "FT",
      "group": "B",
      "home": "Canada",
      "away": "Qatar",
      "venue": "Vancouver",
      "hs": 6,
      "as": 0,
      "statusShort": "FT"
    },
    {
      "date": "Jun 18",
      "isoDate": "2026-06-18",
      "time": "FT",
      "group": "A",
      "home": "Czechia",
      "away": "South Africa",
      "venue": "Atlanta",
      "hs": 1,
      "as": 1,
      "statusShort": "FT"
    },
    {
      "date": "Jun 18",
      "isoDate": "2026-06-18",
      "time": "FT",
      "group": "A",
      "home": "Mexico",
      "away": "South Korea",
      "venue": "Guadalajara",
      "hs": 1,
      "as": 0,
      "statusShort": "FT"
    },
    {
      "date": "Jun 18",
      "isoDate": "2026-06-18",
      "time": "FT",
      "group": "B",
      "home": "Switzerland",
      "away": "Bosnia and Herzegovina",
      "venue": "Los Angeles",
      "hs": 4,
      "as": 1,
      "statusShort": "FT"
    },
    {
      "date": "Jun 19",
      "isoDate": "2026-06-19",
      "time": "FT",
      "group": "C",
      "home": "Brazil",
      "away": "Haiti",
      "venue": "Philadelphia",
      "hs": 3,
      "as": 0,
      "statusShort": "FT"
    },
    {
      "date": "Jun 19",
      "isoDate": "2026-06-19",
      "time": "FT",
      "group": "C",
      "home": "Scotland",
      "away": "Morocco",
      "venue": "Boston",
      "hs": 0,
      "as": 1,
      "statusShort": "FT"
    },
    {
      "date": "Jun 19",
      "isoDate": "2026-06-19",
      "time": "FT",
      "group": "D",
      "home": "Turkiye",
      "away": "Paraguay",
      "venue": "San Francisco Bay Area",
      "hs": 0,
      "as": 1,
      "statusShort": "FT"
    },
    {
      "date": "Jun 19",
      "isoDate": "2026-06-19",
      "time": "FT",
      "group": "D",
      "home": "United States",
      "away": "Australia",
      "venue": "Seattle",
      "hs": 2,
      "as": 0,
      "statusShort": "FT"
    },
    {
      "date": "Jun 20",
      "isoDate": "2026-06-20",
      "time": "FT",
      "group": "E",
      "home": "Ecuador",
      "away": "Curacao",
      "venue": "Kansas City",
      "hs": 0,
      "as": 0,
      "statusShort": "FT"
    },
    {
      "date": "Jun 20",
      "isoDate": "2026-06-20",
      "time": "FT",
      "group": "E",
      "home": "Germany",
      "away": "Cote d'Ivoire",
      "venue": "Toronto",
      "hs": 2,
      "as": 1,
      "statusShort": "FT"
    },
    {
      "date": "Jun 20",
      "isoDate": "2026-06-20",
      "time": "FT",
      "group": "F",
      "home": "Netherlands",
      "away": "Sweden",
      "venue": "Houston",
      "hs": 5,
      "as": 1,
      "statusShort": "FT"
    },
    {
      "date": "Jun 20",
      "isoDate": "2026-06-20",
      "time": "FT",
      "group": "F",
      "home": "Tunisia",
      "away": "Japan",
      "venue": "Monterrey",
      "hs": 0,
      "as": 4,
      "statusShort": "FT"
    },
    {
      "date": "Jun 21",
      "isoDate": "2026-06-21",
      "time": "FT",
      "group": "G",
      "home": "Belgium",
      "away": "Iran",
      "venue": "Los Angeles",
      "hs": 0,
      "as": 0,
      "statusShort": "FT"
    },
    {
      "date": "Jun 21",
      "isoDate": "2026-06-21",
      "time": "FT",
      "group": "G",
      "home": "New Zealand",
      "away": "Egypt",
      "venue": "Vancouver",
      "hs": 1,
      "as": 3,
      "statusShort": "FT"
    },
    {
      "date": "Jun 21",
      "isoDate": "2026-06-21",
      "time": "FT",
      "group": "H",
      "home": "Spain",
      "away": "Saudi Arabia",
      "venue": "Atlanta",
      "hs": 4,
      "as": 0,
      "statusShort": "FT"
    },
    {
      "date": "Jun 21",
      "isoDate": "2026-06-21",
      "time": "FT",
      "group": "H",
      "home": "Uruguay",
      "away": "Cape Verde",
      "venue": "Miami",
      "hs": 2,
      "as": 2,
      "statusShort": "FT"
    },
    {
      "date": "Jun 22",
      "isoDate": "2026-06-22",
      "time": "FT",
      "group": "J",
      "home": "Argentina",
      "away": "Austria",
      "venue": "Dallas",
      "hs": 2,
      "as": 0,
      "statusShort": "FT"
    },
    {
      "date": "Jun 22",
      "isoDate": "2026-06-22",
      "time": "FT",
      "group": "I",
      "home": "France",
      "away": "Iraq",
      "venue": "Philadelphia",
      "hs": 3,
      "as": 0,
      "statusShort": "FT"
    },
    {
      "date": "Jun 22",
      "isoDate": "2026-06-22",
      "time": "FT",
      "group": "J",
      "home": "Jordan",
      "away": "Algeria",
      "venue": "San Francisco Bay Area",
      "hs": 1,
      "as": 2,
      "statusShort": "FT"
    },
    {
      "date": "Jun 22",
      "isoDate": "2026-06-22",
      "time": "FT",
      "group": "I",
      "home": "Norway",
      "away": "Senegal",
      "venue": "New York/New Jersey",
      "hs": 3,
      "as": 2,
      "statusShort": "FT"
    },
    {
      "date": "Jun 23",
      "isoDate": "2026-06-23",
      "time": "FT",
      "group": "K",
      "home": "Colombia",
      "away": "DR Congo",
      "venue": "Guadalajara",
      "hs": 1,
      "as": 0,
      "statusShort": "FT"
    },
    {
      "date": "Jun 23",
      "isoDate": "2026-06-23",
      "time": "FT",
      "group": "L",
      "home": "England",
      "away": "Ghana",
      "venue": "Boston",
      "hs": 0,
      "as": 0,
      "statusShort": "FT"
    },
    {
      "date": "Jun 23",
      "isoDate": "2026-06-23",
      "time": "FT",
      "group": "L",
      "home": "Panama",
      "away": "Croatia",
      "venue": "Toronto",
      "hs": 0,
      "as": 1,
      "statusShort": "FT"
    },
    {
      "date": "Jun 23",
      "isoDate": "2026-06-23",
      "time": "FT",
      "group": "K",
      "home": "Portugal",
      "away": "Uzbekistan",
      "venue": "Houston",
      "hs": 5,
      "as": 0,
      "statusShort": "FT"
    },
    {
      "date": "Jun 24",
      "isoDate": "2026-06-24",
      "time": "FT",
      "group": "B",
      "home": "Bosnia and Herzegovina",
      "away": "Qatar",
      "venue": "Seattle",
      "hs": 3,
      "as": 1,
      "statusShort": "FT"
    },
    {
      "date": "Jun 24",
      "isoDate": "2026-06-24",
      "time": "FT",
      "group": "A",
      "home": "Czechia",
      "away": "Mexico",
      "venue": "Mexico City",
      "hs": 0,
      "as": 3,
      "statusShort": "FT"
    },
    {
      "date": "Jun 24",
      "isoDate": "2026-06-24",
      "time": "FT",
      "group": "C",
      "home": "Morocco",
      "away": "Haiti",
      "venue": "Atlanta",
      "hs": 4,
      "as": 2,
      "statusShort": "FT"
    },
    {
      "date": "Jun 24",
      "isoDate": "2026-06-24",
      "time": "FT",
      "group": "C",
      "home": "Scotland",
      "away": "Brazil",
      "venue": "Miami",
      "hs": 0,
      "as": 3,
      "statusShort": "FT"
    },
    {
      "date": "Jun 24",
      "isoDate": "2026-06-24",
      "time": "FT",
      "group": "A",
      "home": "South Africa",
      "away": "South Korea",
      "venue": "Monterrey",
      "hs": 1,
      "as": 0,
      "statusShort": "FT"
    },
    {
      "date": "Jun 24",
      "isoDate": "2026-06-24",
      "time": "FT",
      "group": "B",
      "home": "Switzerland",
      "away": "Canada",
      "venue": "Vancouver",
      "hs": 2,
      "as": 1,
      "statusShort": "FT"
    },
    {
      "date": "Jun 25",
      "isoDate": "2026-06-25",
      "time": "FT",
      "group": "E",
      "home": "Curacao",
      "away": "Cote d'Ivoire",
      "venue": "Philadelphia",
      "hs": 0,
      "as": 2,
      "statusShort": "FT"
    },
    {
      "date": "Jun 25",
      "isoDate": "2026-06-25",
      "time": "FT",
      "group": "E",
      "home": "Ecuador",
      "away": "Germany",
      "venue": "New York/New Jersey",
      "hs": 2,
      "as": 1,
      "statusShort": "FT"
    },
    {
      "date": "Jun 25",
      "isoDate": "2026-06-25",
      "time": "FT",
      "group": "F",
      "home": "Japan",
      "away": "Sweden",
      "venue": "Dallas",
      "hs": 1,
      "as": 1,
      "statusShort": "FT"
    },
    {
      "date": "Jun 25",
      "isoDate": "2026-06-25",
      "time": "FT",
      "group": "D",
      "home": "Paraguay",
      "away": "Australia",
      "venue": "San Francisco Bay Area",
      "hs": 0,
      "as": 0,
      "statusShort": "FT"
    },
    {
      "date": "Jun 25",
      "isoDate": "2026-06-25",
      "time": "FT",
      "group": "F",
      "home": "Tunisia",
      "away": "Netherlands",
      "venue": "Kansas City",
      "hs": 1,
      "as": 3,
      "statusShort": "FT"
    },
    {
      "date": "Jun 25",
      "isoDate": "2026-06-25",
      "time": "FT",
      "group": "D",
      "home": "Turkiye",
      "away": "United States",
      "venue": "Los Angeles",
      "hs": 3,
      "as": 2,
      "statusShort": "FT"
    },
    {
      "date": "Jun 26",
      "isoDate": "2026-06-26",
      "time": "FT",
      "group": "H",
      "home": "Cape Verde",
      "away": "Saudi Arabia",
      "venue": "Houston",
      "hs": 0,
      "as": 0,
      "statusShort": "FT"
    },
    {
      "date": "Jun 26",
      "isoDate": "2026-06-26",
      "time": "FT",
      "group": "G",
      "home": "Egypt",
      "away": "Iran",
      "venue": "Seattle",
      "hs": 1,
      "as": 1,
      "statusShort": "FT"
    },
    {
      "date": "Jun 26",
      "isoDate": "2026-06-26",
      "time": "FT",
      "group": "G",
      "home": "New Zealand",
      "away": "Belgium",
      "venue": "Vancouver",
      "hs": 1,
      "as": 5,
      "statusShort": "FT"
    },
    {
      "date": "Jun 26",
      "isoDate": "2026-06-26",
      "time": "FT",
      "group": "I",
      "home": "Norway",
      "away": "France",
      "venue": "Boston",
      "hs": 1,
      "as": 4,
      "statusShort": "FT"
    },
    {
      "date": "Jun 26",
      "isoDate": "2026-06-26",
      "time": "FT",
      "group": "I",
      "home": "Senegal",
      "away": "Iraq",
      "venue": "Toronto",
      "hs": 5,
      "as": 0,
      "statusShort": "FT"
    },
    {
      "date": "Jun 26",
      "isoDate": "2026-06-26",
      "time": "FT",
      "group": "H",
      "home": "Uruguay",
      "away": "Spain",
      "venue": "Guadalajara",
      "hs": 0,
      "as": 1,
      "statusShort": "FT"
    },
    {
      "date": "Jun 27",
      "isoDate": "2026-06-27",
      "time": "FT",
      "group": "J",
      "home": "Algeria",
      "away": "Austria",
      "venue": "Kansas City",
      "hs": 3,
      "as": 3,
      "statusShort": "FT"
    },
    {
      "date": "Jun 27",
      "isoDate": "2026-06-27",
      "time": "FT",
      "group": "K",
      "home": "Colombia",
      "away": "Portugal",
      "venue": "Miami",
      "hs": 0,
      "as": 0,
      "statusShort": "FT"
    },
    {
      "date": "Jun 27",
      "isoDate": "2026-06-27",
      "time": "FT",
      "group": "L",
      "home": "Croatia",
      "away": "Ghana",
      "venue": "Philadelphia",
      "hs": 2,
      "as": 1,
      "statusShort": "FT"
    },
    {
      "date": "Jun 27",
      "isoDate": "2026-06-27",
      "time": "FT",
      "group": "K",
      "home": "DR Congo",
      "away": "Uzbekistan",
      "venue": "Atlanta",
      "hs": 3,
      "as": 1,
      "statusShort": "FT"
    },
    {
      "date": "Jun 27",
      "isoDate": "2026-06-27",
      "time": "FT",
      "group": "J",
      "home": "Jordan",
      "away": "Argentina",
      "venue": "Dallas",
      "hs": 1,
      "as": 3,
      "statusShort": "FT"
    },
    {
      "date": "Jun 27",
      "isoDate": "2026-06-27",
      "time": "FT",
      "group": "L",
      "home": "Panama",
      "away": "England",
      "venue": "New York/New Jersey",
      "hs": 0,
      "as": 2,
      "statusShort": "FT"
    }
  ],
  "knockout": [
    {
      "n": 73,
      "round": "Round of 32",
      "isoDate": "2026-06-28",
      "date": "Jun 28",
      "venue": "Inglewood",
      "homeLabel": "RU A",
      "awayLabel": "RU B",
      "home": "South Africa",
      "away": "Canada",
      "time": "FT",
      "statusShort": "FT",
      "winner": "Canada",
      "hs": 0,
      "as": 1
    },
    {
      "n": 74,
      "round": "Round of 32",
      "isoDate": "2026-06-29",
      "date": "Jun 29",
      "venue": "Foxborough",
      "homeLabel": "W E",
      "awayLabel": "3rd A/B/C/D/F",
      "home": "Germany",
      "away": "Paraguay",
      "time": "FT",
      "statusShort": "FT-Pens",
      "winner": "Paraguay",
      "hs": 1,
      "as": 1,
      "hps": 3,
      "aps": 4
    },
    {
      "n": 75,
      "round": "Round of 32",
      "isoDate": "2026-06-29",
      "date": "Jun 29",
      "venue": "Guadalupe",
      "homeLabel": "W F",
      "awayLabel": "RU C",
      "home": "Netherlands",
      "away": "Morocco",
      "time": "FT",
      "statusShort": "FT-Pens",
      "winner": "Morocco",
      "hs": 1,
      "as": 1,
      "hps": 2,
      "aps": 3
    },
    {
      "n": 76,
      "round": "Round of 32",
      "isoDate": "2026-06-29",
      "date": "Jun 29",
      "venue": "Houston",
      "homeLabel": "W C",
      "awayLabel": "RU F",
      "home": "Brazil",
      "away": "Japan",
      "time": "FT",
      "statusShort": "FT",
      "winner": "Brazil",
      "hs": 2,
      "as": 1
    },
    {
      "n": 77,
      "round": "Round of 32",
      "isoDate": "2026-06-30",
      "date": "Jun 30",
      "venue": "New York/New Jersey",
      "homeLabel": "W I",
      "awayLabel": "3rd C/D/F/G/H",
      "home": "France",
      "away": "Sweden",
      "time": "FT",
      "statusShort": "FT",
      "winner": "France",
      "hs": 3,
      "as": 0
    },
    {
      "n": 78,
      "round": "Round of 32",
      "isoDate": "2026-06-30",
      "date": "Jun 30",
      "venue": "Arlington",
      "homeLabel": "RU E",
      "awayLabel": "RU I",
      "home": "Cote d'Ivoire",
      "away": "Norway",
      "time": "FT",
      "statusShort": "FT",
      "winner": "Norway",
      "hs": 1,
      "as": 2
    },
    {
      "n": 79,
      "round": "Round of 32",
      "isoDate": "2026-06-30",
      "date": "Jun 30",
      "venue": "Mexico City",
      "homeLabel": "W A",
      "awayLabel": "3rd C/E/F/H/I",
      "home": "Mexico",
      "away": "Ecuador",
      "time": "FT",
      "statusShort": "FT",
      "winner": "Mexico",
      "hs": 2,
      "as": 0
    },
    {
      "n": 80,
      "round": "Round of 32",
      "isoDate": "2026-07-01",
      "date": "Jul 1",
      "venue": "Atlanta",
      "homeLabel": "W L",
      "awayLabel": "3rd E/H/I/J/K",
      "home": "England",
      "away": "DR Congo",
      "time": "FT",
      "statusShort": "FT",
      "winner": "England",
      "hs": 2,
      "as": 1
    },
    {
      "n": 81,
      "round": "Round of 32",
      "isoDate": "2026-07-01",
      "date": "Jul 1",
      "venue": "Santa Clara",
      "homeLabel": "W D",
      "awayLabel": "3rd B/E/F/I/J",
      "home": "United States",
      "away": "Bosnia and Herzegovina",
      "time": "Upcoming",
      "statusShort": "Scheduled",
      "winner": null
    },
    {
      "n": 82,
      "round": "Round of 32",
      "isoDate": "2026-07-01",
      "date": "Jul 1",
      "venue": "Seattle",
      "homeLabel": "W G",
      "awayLabel": "3rd A/E/H/I/J",
      "home": "Belgium",
      "away": "Senegal",
      "time": "FT",
      "statusShort": "AET",
      "winner": "Belgium",
      "hs": 3,
      "as": 2
    },
    {
      "n": 83,
      "round": "Round of 32",
      "isoDate": "2026-07-02",
      "date": "Jul 2",
      "venue": "Toronto",
      "homeLabel": "RU K",
      "awayLabel": "RU L",
      "home": "Portugal",
      "away": "Croatia",
      "time": "Upcoming",
      "statusShort": "Scheduled",
      "winner": null
    },
    {
      "n": 84,
      "round": "Round of 32",
      "isoDate": "2026-07-02",
      "date": "Jul 2",
      "venue": "Inglewood",
      "homeLabel": "W H",
      "awayLabel": "RU J",
      "home": "Spain",
      "away": "Austria",
      "time": "Upcoming",
      "statusShort": "Scheduled",
      "winner": null
    },
    {
      "n": 85,
      "round": "Round of 32",
      "isoDate": "2026-07-02",
      "date": "Jul 2",
      "venue": "Vancouver",
      "homeLabel": "W B",
      "awayLabel": "3rd E/F/G/I/J",
      "home": "Switzerland",
      "away": "Algeria",
      "time": "Upcoming",
      "statusShort": "Scheduled",
      "winner": null
    },
    {
      "n": 86,
      "round": "Round of 32",
      "isoDate": "2026-07-03",
      "date": "Jul 3",
      "venue": "Miami Gardens",
      "homeLabel": "W J",
      "awayLabel": "RU H",
      "home": "Argentina",
      "away": "Cape Verde",
      "time": "Upcoming",
      "statusShort": "Scheduled",
      "winner": null
    },
    {
      "n": 87,
      "round": "Round of 32",
      "isoDate": "2026-07-03",
      "date": "Jul 3",
      "venue": "Kansas City",
      "homeLabel": "W K",
      "awayLabel": "3rd D/E/I/J/L",
      "home": "Colombia",
      "away": "Ghana",
      "time": "Upcoming",
      "statusShort": "Scheduled",
      "winner": null
    },
    {
      "n": 88,
      "round": "Round of 32",
      "isoDate": "2026-07-03",
      "date": "Jul 3",
      "venue": "Arlington",
      "homeLabel": "RU D",
      "awayLabel": "RU G",
      "home": "Australia",
      "away": "Egypt",
      "time": "Upcoming",
      "statusShort": "Scheduled",
      "winner": null
    },
    {
      "n": 89,
      "round": "Round of 16",
      "isoDate": "2026-07-04",
      "date": "Jul 4",
      "venue": "Philadelphia",
      "homeLabel": "W 74",
      "awayLabel": "W 77",
      "home": "Paraguay",
      "away": "France",
      "time": "Upcoming",
      "statusShort": "Scheduled",
      "winner": null
    },
    {
      "n": 90,
      "round": "Round of 16",
      "isoDate": "2026-07-04",
      "date": "Jul 4",
      "venue": "Houston",
      "homeLabel": "W 73",
      "awayLabel": "W 75",
      "home": "Canada",
      "away": "Morocco",
      "time": "Upcoming",
      "statusShort": "Scheduled",
      "winner": null
    },
    {
      "n": 91,
      "round": "Round of 16",
      "isoDate": "2026-07-05",
      "date": "Jul 5",
      "venue": "New York/New Jersey",
      "homeLabel": "W 76",
      "awayLabel": "W 78",
      "home": "Brazil",
      "away": "Norway",
      "time": "Upcoming",
      "statusShort": "Scheduled",
      "winner": null
    },
    {
      "n": 92,
      "round": "Round of 16",
      "isoDate": "2026-07-05",
      "date": "Jul 5",
      "venue": "Mexico City",
      "homeLabel": "W 79",
      "awayLabel": "W 80",
      "home": "Mexico",
      "away": "England",
      "time": "Upcoming",
      "statusShort": "Scheduled",
      "winner": null
    },
    {
      "n": 93,
      "round": "Round of 16",
      "isoDate": "2026-07-06",
      "date": "Jul 6",
      "venue": "Arlington",
      "homeLabel": "W 83",
      "awayLabel": "W 84",
      "home": null,
      "away": null,
      "time": "Upcoming",
      "statusShort": "",
      "winner": null
    },
    {
      "n": 94,
      "round": "Round of 16",
      "isoDate": "2026-07-06",
      "date": "Jul 6",
      "venue": "Seattle",
      "homeLabel": "W 81",
      "awayLabel": "W 82",
      "home": null,
      "away": "Belgium",
      "time": "Upcoming",
      "statusShort": "",
      "winner": null
    },
    {
      "n": 95,
      "round": "Round of 16",
      "isoDate": "2026-07-07",
      "date": "Jul 7",
      "venue": "Atlanta",
      "homeLabel": "W 86",
      "awayLabel": "W 88",
      "home": null,
      "away": null,
      "time": "Upcoming",
      "statusShort": "",
      "winner": null
    },
    {
      "n": 96,
      "round": "Round of 16",
      "isoDate": "2026-07-07",
      "date": "Jul 7",
      "venue": "Vancouver",
      "homeLabel": "W 85",
      "awayLabel": "W 87",
      "home": null,
      "away": null,
      "time": "Upcoming",
      "statusShort": "",
      "winner": null
    },
    {
      "n": 97,
      "round": "Quarter-finals",
      "isoDate": "2026-07-09",
      "date": "Jul 9",
      "venue": "Foxborough",
      "homeLabel": "W 89",
      "awayLabel": "W 90",
      "home": null,
      "away": null,
      "time": "Upcoming",
      "statusShort": "",
      "winner": null
    },
    {
      "n": 98,
      "round": "Quarter-finals",
      "isoDate": "2026-07-10",
      "date": "Jul 10",
      "venue": "Inglewood",
      "homeLabel": "W 93",
      "awayLabel": "W 94",
      "home": null,
      "away": null,
      "time": "Upcoming",
      "statusShort": "",
      "winner": null
    },
    {
      "n": 99,
      "round": "Quarter-finals",
      "isoDate": "2026-07-11",
      "date": "Jul 11",
      "venue": "Miami Gardens",
      "homeLabel": "W 91",
      "awayLabel": "W 92",
      "home": null,
      "away": null,
      "time": "Upcoming",
      "statusShort": "",
      "winner": null
    },
    {
      "n": 100,
      "round": "Quarter-finals",
      "isoDate": "2026-07-11",
      "date": "Jul 11",
      "venue": "Kansas City",
      "homeLabel": "W 95",
      "awayLabel": "W 96",
      "home": null,
      "away": null,
      "time": "Upcoming",
      "statusShort": "",
      "winner": null
    },
    {
      "n": 101,
      "round": "Semi-finals",
      "isoDate": "2026-07-14",
      "date": "Jul 14",
      "venue": "Arlington",
      "homeLabel": "W 97",
      "awayLabel": "W 98",
      "home": null,
      "away": null,
      "time": "Upcoming",
      "statusShort": "",
      "winner": null
    },
    {
      "n": 102,
      "round": "Semi-finals",
      "isoDate": "2026-07-15",
      "date": "Jul 15",
      "venue": "Atlanta",
      "homeLabel": "W 99",
      "awayLabel": "W 100",
      "home": null,
      "away": null,
      "time": "Upcoming",
      "statusShort": "",
      "winner": null
    },
    {
      "n": 103,
      "round": "Third place",
      "isoDate": "2026-07-18",
      "date": "Jul 18",
      "venue": "Miami Gardens",
      "homeLabel": "L 101",
      "awayLabel": "L 102",
      "home": null,
      "away": null,
      "time": "Upcoming",
      "statusShort": "",
      "winner": null
    },
    {
      "n": 104,
      "round": "Final",
      "isoDate": "2026-07-19",
      "date": "Jul 19",
      "venue": "New York/New Jersey",
      "homeLabel": "W 101",
      "awayLabel": "W 102",
      "home": null,
      "away": null,
      "time": "Upcoming",
      "statusShort": "",
      "winner": null
    }
  ]
}
